README.rst
setup.py
src/miraclelight/__init__.py
src/miraclelight.egg-info/PKG-INFO
src/miraclelight.egg-info/SOURCES.txt
src/miraclelight.egg-info/dependency_links.txt
src/miraclelight.egg-info/entry_points.txt
src/miraclelight.egg-info/not-zip-safe
src/miraclelight.egg-info/top_level.txt