Metadata-Version: 1.1
Name: miraclelight
Version: 0.1
Summary: The Python TestRunner by battle heroine "Pretty Cure".
Home-page: https://github.com/drillbits/miraclelight
Author: Jiro Nejime
Author-email: neji@drillbits.jp
License: MIT
Platform: UNKNOWN
Classifier: Development Status :: 3 - Alpha
Classifier: Intended Audience :: Developers
Classifier: Programming Language :: Python
Classifier: Programming Language :: Python :: 3.3
Classifier: Topic :: Utilities
Classifier: License :: OSI Approved :: MIT License
